setup.py
distributions/Binomialdistribution.py
distributions/Gaussiandistribution.py
distributions/Generaldistribution.py
distributions/__init__.py
nanoint_distributions.egg-info/PKG-INFO
nanoint_distributions.egg-info/SOURCES.txt
nanoint_distributions.egg-info/dependency_links.txt
nanoint_distributions.egg-info/not-zip-safe
nanoint_distributions.egg-info/top_level.txt