Metadata-Version: 1.0
Name: nanoint-distributions
Version: 0.2
Summary: Gaussian and Binomial distributions
Home-page: UNKNOWN
Author: Nursultan Agzhigitov
Author-email: nursultan.agzhigitov@gmail.com
License: UNKNOWN
Platform: UNKNOWN
